alibabacloud_searchplat20240529/__init__.py
alibabacloud_searchplat20240529/client.py
alibabacloud_searchplat20240529/models.py
alibabacloud_searchplat20240529-2.3.0.dist-info/LICENSE
alibabacloud_searchplat20240529-2.3.0.dist-info/METADATA
alibabacloud_searchplat20240529-2.3.0.dist-info/WHEEL
alibabacloud_searchplat20240529-2.3.0.dist-info/top_level.txt
alibabacloud_searchplat20240529-2.3.0.dist-info/RECORD
